protomodel/__init__.py
protomodel/__main__.py
protomodel/example/__init__.py
protomodel/example/data.py
protomodel/hello.py
protomodel/message.py
protomodel/rpc.py
protomodel/service.py
protomodel/types/__init__.py
protomodel/types/get_types.py
protomodel/utils/__init__.py
protomodel-0.0.13.dist-info/METADATA
protomodel-0.0.13.dist-info/WHEEL
protomodel-0.0.13.dist-info/entry_points.txt
protomodel-0.0.13.dist-info/RECORD
