Metadata-Version: 2.1
Name: protomodel
Version: 0.0.13
Summary: Python Library to generate proto buffer code from python using type annotations
Author: Pablo España
Author-email: pabloespanab@outlook.com
Requires-Python: >=3.10,<4.0
Classifier: Programming Language :: Python :: 3
Classifier: Programming Language :: Python :: 3.10
Classifier: Programming Language :: Python :: 3.11
Requires-Dist: click (>=8.1.5,<9.0.0)
Requires-Dist: flake8 (>=6.0.0,<7.0.0)
